octohook/__init__.py
octohook/decorators.py
octohook/events.py
octohook/models.py
octohook-0.13.dist-info/METADATA
octohook-0.13.dist-info/WHEEL
octohook-0.13.dist-info/licenses/LICENSE
octohook-0.13.dist-info/RECORD
