Metadata-Version: 2.4
Name: octohook
Version: 0.13
Summary: Typed interactions with Github Webhooks
Author-email: Sridhar Vadlamani <v.sridhar.sreenivas@gmail.com>
License-File: LICENSE
Keywords: github,typed,webhooks
Classifier: Development Status :: 4 - Beta
Classifier: License :: OSI Approved :: MIT License
Classifier: Operating System :: OS Independent
Classifier: Programming Language :: Python :: 3.10
Classifier: Programming Language :: Python :: 3.11
Classifier: Programming Language :: Python :: 3.12
Classifier: Programming Language :: Python :: 3.13
Classifier: Topic :: Software Development :: Libraries
Classifier: Topic :: Software Development :: Libraries :: Python Modules
Requires-Python: >=3.10
